[{"id":32,"posts":null,"followers":601547,"following":744030,"username":"ieldritt0"},
{"id":17,"posts":null,"followers":124069,"following":374840,"username":"htyce1"},
{"id":39,"posts":null,"followers":845514,"following":993818,"username":"bdrinkhill2"},
{"id":92,"posts":null,"followers":290829,"following":119488,"username":"dnuccii3"},
{"id":2,"posts":null,"followers":838446,"following":642329,"username":"lkidson4"},
{"id":14,"posts":null,"followers":610970,"following":84178,"username":"llehrian5"},
{"id":99,"posts":null,"followers":35570,"following":721407,"username":"fanscott6"},
{"id":4,"posts":null,"followers":797203,"following":703001,"username":"wsynder7"},
{"id":66,"posts":null,"followers":653355,"following":752939,"username":"aglaum8"},
{"id":49,"posts":null,"followers":15287,"following":153646,"username":"kbavester9"}]